psdmpy/__init__.py
psdmpy/analysis/__init__.py
psdmpy/analysis/calc.py
psdmpy/analysis/grid.py
psdmpy/conversion/__init__.py
psdmpy/conversion/pandapower.py
psdmpy/errors.py
psdmpy/io/__init__.py
psdmpy/io/utils.py
psdmpy/models/__init__.py
psdmpy/models/enums.py
psdmpy/models/gwr.py
psdmpy/models/input/__init__.py
psdmpy/models/input/connector/__init__.py
psdmpy/models/input/connector/connector.py
psdmpy/models/input/connector/lines.py
psdmpy/models/input/connector/switches.py
psdmpy/models/input/connector/transformer.py
psdmpy/models/input/container/__init__.py
psdmpy/models/input/container/grid.py
psdmpy/models/input/container/mixins.py
psdmpy/models/input/container/participants.py
psdmpy/models/input/container/raw_grid.py
psdmpy/models/input/create/participants.py
psdmpy/models/input/create/thermal.py
psdmpy/models/input/create/utils.py
psdmpy/models/input/entity.py
psdmpy/models/input/node.py
psdmpy/models/input/participant/__init__.py
psdmpy/models/input/participant/bm.py
psdmpy/models/input/participant/charging.py
psdmpy/models/input/participant/em.py
psdmpy/models/input/participant/evcs.py
psdmpy/models/input/participant/evs.py
psdmpy/models/input/participant/fixed_feed_in.py
psdmpy/models/input/participant/hp.py
psdmpy/models/input/participant/load.py
psdmpy/models/input/participant/participant.py
psdmpy/models/input/participant/pv.py
psdmpy/models/input/participant/storage.py
psdmpy/models/input/participant/wec.py
psdmpy/models/input/thermal/bus.py
psdmpy/models/input/thermal/grid.py
psdmpy/models/input/thermal/house.py
psdmpy/models/primary_data.py
psdmpy/models/result/__init__.py
psdmpy/models/result/container/__init__.py
psdmpy/models/result/container/grid.py
psdmpy/models/result/container/participants.py
psdmpy/models/result/entity.py
psdmpy/models/result/flex_option.py
psdmpy/models/result/grid/__init__.py
psdmpy/models/result/grid/connector.py
psdmpy/models/result/grid/enhanced_node.py
psdmpy/models/result/grid/node.py
psdmpy-0.0.1rc2.dist-info/LICENSE
psdmpy-0.0.1rc2.dist-info/METADATA
psdmpy-0.0.1rc2.dist-info/WHEEL
psdmpy-0.0.1rc2.dist-info/RECORD
